privalyse_cli-0.3.3.dist-info/licenses/LICENSE
privalyse_scanner/__init__.py
privalyse_scanner/cli.py
privalyse_scanner/analyzers/__init__.py
privalyse_scanner/analyzers/base_analyzer.py
privalyse_scanner/analyzers/compliance_analyzer.py
privalyse_scanner/analyzers/cross_file_analyzer.py
privalyse_scanner/analyzers/crypto_analyzer.py
privalyse_scanner/analyzers/infrastructure_analyzer.py
privalyse_scanner/analyzers/injection_analyzer.py
privalyse_scanner/analyzers/javascript_analyzer.py
privalyse_scanner/analyzers/python_analyzer.py
privalyse_scanner/analyzers/security_analyzer.py
privalyse_scanner/config/framework_patterns.py
privalyse_scanner/core/__init__.py
privalyse_scanner/core/file_iterator.py
privalyse_scanner/core/import_resolver.py
privalyse_scanner/core/route_resolver.py
privalyse_scanner/core/scanner.py
privalyse_scanner/core/score_recommendation.py
privalyse_scanner/core/sink_resolver.py
privalyse_scanner/core/symbol_table.py
privalyse_scanner/exporters/__init__.py
privalyse_scanner/exporters/html_exporter.py
privalyse_scanner/exporters/json_exporter.py
privalyse_scanner/exporters/markdown_exporter.py
privalyse_scanner/exporters/report_generator.py
privalyse_scanner/exporters/sarif_exporter.py
privalyse_scanner/models/__init__.py
privalyse_scanner/models/config.py
privalyse_scanner/models/finding.py
privalyse_scanner/models/graph.py
privalyse_scanner/models/taint.py
privalyse_scanner/parsers/__init__.py
privalyse_scanner/utils/__init__.py
privalyse_scanner/utils/classification.py
privalyse_scanner/utils/compliance_mapper.py
privalyse_scanner/utils/config_loader.py
privalyse_scanner/utils/deterministic_rules.py
privalyse_scanner/utils/helpers.py
privalyse_scanner/utils/ui.py
privalyse_scanner/utils/visualizer.py
privalyse_cli-0.3.3.dist-info/METADATA
privalyse_cli-0.3.3.dist-info/WHEEL
privalyse_cli-0.3.3.dist-info/entry_points.txt
privalyse_cli-0.3.3.dist-info/top_level.txt
privalyse_cli-0.3.3.dist-info/RECORD
