Metadata-Version: 2.4
Name: privalyse-cli
Version: 0.3.3
Summary: Privacy scanner with GDPR compliance reports - Zero config, instant insights
Author-email: Privalyse <hello@privalyse.com>
License: MIT
Project-URL: Repository, https://github.com/privalyse/privalyse-cli
Project-URL: Issues, https://github.com/privalyse/privalyse-cli/issues
Project-URL: Changelog, https://github.com/privalyse/privalyse-cli/blob/main/CHANGELOG.md
Keywords: privacy,gdpr,compliance,security,scanner,pii,data-protection,audit,sast,code-analysis
Classifier: Development Status :: 3 - Alpha
Classifier: Intended Audience :: Developers
Classifier: License :: OSI Approved :: MIT License
Classifier: Programming Language :: Python :: 3
Classifier: Programming Language :: Python :: 3.8
Classifier: Programming Language :: Python :: 3.9
Classifier: Programming Language :: Python :: 3.10
Classifier: Programming Language :: Python :: 3.11
Classifier: Programming Language :: Python :: 3.12
Classifier: Topic :: Security
Classifier: Topic :: Software Development :: Quality Assurance
Classifier: Topic :: Software Development :: Testing
Classifier: Operating System :: OS Independent
Requires-Python: >=3.8
License-File: LICENSE
Requires-Dist: rich>=13.0.0
Requires-Dist: esprima>=4.0.1
Provides-Extra: dev
Requires-Dist: pytest>=7.0.0; extra == "dev"
Requires-Dist: pytest-cov>=4.0.0; extra == "dev"
Requires-Dist: black>=23.0.0; extra == "dev"
Requires-Dist: mypy>=1.0.0; extra == "dev"
Requires-Dist: ruff>=0.1.0; extra == "dev"
Dynamic: license-file
